firststreet/__init__.py
firststreet/__main__.py
firststreet/errors.py
firststreet/http_util.py
firststreet/util.py
firststreet/api/__init__.py
firststreet/api/adaptation.py
firststreet/api/api.py
firststreet/api/csv_format.py
firststreet/api/economic.py
firststreet/api/environmental.py
firststreet/api/fema.py
firststreet/api/historic.py
firststreet/api/location.py
firststreet/api/probability.py
firststreet/api/tile.py
firststreet/models/__init__.py
firststreet/models/adaptation.py
firststreet/models/api.py
firststreet/models/economic.py
firststreet/models/environmental.py
firststreet/models/fema.py
firststreet/models/geometry.py
firststreet/models/historic.py
firststreet/models/location.py
firststreet/models/probability.py
firststreet/models/tile.py
fsf_api_access_python-2.3.6.dist-info/LICENSE
fsf_api_access_python-2.3.6.dist-info/METADATA
fsf_api_access_python-2.3.6.dist-info/WHEEL
fsf_api_access_python-2.3.6.dist-info/top_level.txt
fsf_api_access_python-2.3.6.dist-info/RECORD
