Metadata-Version: 2.1
Name: fsf-api-access-python
Version: 2.3.6
Summary: A Python API Access Client for the First Street Foundation API
Home-page: https://github.com/FirstStreet/fsf_api_access_python
Author: Kelvin
Author-email: kelvin@firststreet.org
License: MIT
Project-URL: First Street Foundation Website, https://firststreet.org/
Project-URL: API Product Data Dictionary, https://docs.firststreet.dev/docs
Platform: UNKNOWN
Classifier: License :: OSI Approved :: MIT License
Classifier: Topic :: Scientific/Engineering
Classifier: Topic :: Scientific/Engineering :: Hydrology
Classifier: Programming Language :: Python :: 3
Classifier: Programming Language :: Python :: 3.7
Classifier: Programming Language :: Python :: 3.8
Requires-Python: >=3.7
Requires-Dist: aiohttp (>=3.6.2)
Requires-Dist: pandas (>=1.0.5)
Requires-Dist: Shapely (>=1.7.0)
Requires-Dist: tqdm (>=4.46.1)
Requires-Dist: nest-asyncio (>=1.3.3)
Requires-Dist: requests (>=2.24.0)
Requires-Dist: certifi (>=2020.6.20)
Requires-Dist: asyncio-throttle (>=1.0.1)
Provides-Extra: testing
Requires-Dist: pytest ; extra == 'testing'
